simo_zwave/__init__.py
simo_zwave/auto_urls.py
simo_zwave/base_types.py
simo_zwave/controllers.py
simo_zwave/dynamic_settings.py
simo_zwave/forms.py
simo_zwave/gateways.py
simo_zwave/utils.py
simo_zwave/views.py
simo_zwave/__pycache__/__init__.cpython-312.pyc
simo_zwave/__pycache__/__init__.cpython-38.pyc
simo_zwave/__pycache__/auto_urls.cpython-312.pyc
simo_zwave/__pycache__/auto_urls.cpython-38.pyc
simo_zwave/__pycache__/controllers.cpython-312.pyc
simo_zwave/__pycache__/controllers.cpython-38.pyc
simo_zwave/__pycache__/dynamic_settings.cpython-312.pyc
simo_zwave/__pycache__/dynamic_settings.cpython-38.pyc
simo_zwave/__pycache__/forms.cpython-312.pyc
simo_zwave/__pycache__/forms.cpython-38.pyc
simo_zwave/__pycache__/gateways.cpython-312.pyc
simo_zwave/__pycache__/gateways.cpython-38.pyc
simo_zwave/__pycache__/utils.cpython-312.pyc
simo_zwave/__pycache__/utils.cpython-38.pyc
simo_zwave/__pycache__/views.cpython-312.pyc
simo_zwave/__pycache__/views.cpython-38.pyc
simo_zwave/templates/add_zwave_node.html
simo_zwave/templates/remove_zwave_node.html
simo_zwave/templates/zwave_node_choose_gateway.html
simo_zwave/templates/zwave_nodes.html
simo_zwave/templates/admin/zwave/library_update_btn.html
simo_zwave/templates/admin/zwave/zwavenode/change_list_object_tools.html
simo_zwave-2.2.4.dist-info/licenses/LICENSE.md
simo_zwave-2.2.4.dist-info/METADATA
simo_zwave-2.2.4.dist-info/WHEEL
simo_zwave-2.2.4.dist-info/top_level.txt
simo_zwave-2.2.4.dist-info/RECORD
