Metadata-Version: 2.4
Name: simo-zwave
Version: 2.2.4
Summary: Z-Wave JS integration for SIMO.io
Author-email: "Simon V." <simon@simo.io>
Project-URL: Homepage, https://github.com/SIMO-io/simo-zwave
Project-URL: Issues, https://github.com/SIMO-io/simo-zwave/issues
Classifier: Programming Language :: Python :: 3
Classifier: License :: OSI Approved :: MIT License
Classifier: Operating System :: OS Independent
Requires-Python: >=3.8
License-File: LICENSE.md
Requires-Dist: simo>=3.1.7
Requires-Dist: zwave-js-server-python>=0.67.1
Dynamic: license-file
